{"cameraMode":{"drawMode":0,"name":"Shaded","section":"Shading Mode"},"sceneLighting":false,"audioPlay":false,"sceneViewState":{"showFog":true,"showMaterialUpdate":false,"showSkybox":false,"showFlares":true,"showImageEffects":true,"showParticleSystems":true},"in2DMode":false,"pivot":{"x":353.5900573730469,"y":64.75003051757813,"z":116.78584289550781},"rotation":{"x":-0.01743892952799797,"y":0.73150634765625,"z":0.0063307275995612148,"w":-0.6843807697296143},"size":84.99620056152344,"orthographic":false}